[{"id":"6281340120681@s.whatsapp.net","limit":3},{"id":"6285343788098@s.whatsapp.net","limit":-103754},{"id":"6289634511977@s.whatsapp.net","limit":5},{"id":"6281337113622@s.whatsapp.net","limit":2},{"id":"6282123038200@s.whatsapp.net","limit":4},{"id":"601165652170@s.whatsapp.net","limit":2},{"id":"6282153872577@s.whatsapp.net","limit":0},{"id":"6283179114375@s.whatsapp.net","limit":4},{"id":"6285748189392@s.whatsapp.net","limit":19},{"id":"60169723748@s.whatsapp.net","limit":3},{"id":"6283805220809@s.whatsapp.net","limit":4},{"id":"6285724662115@s.whatsapp.net","limit":1},{"id":"6281315051704@s.whatsapp.net","limit":6},{"id":"6282119328901@s.whatsapp.net","limit":6},{"id":"6285226253943@s.whatsapp.net","limit":15},{"id":"6281218203710@s.whatsapp.net","limit":2},{"id":"6282225504450@s.whatsapp.net","limit":11},{"id":"628562813200@s.whatsapp.net","limit":1},{"id":"6283877044303@s.whatsapp.net","limit":-396},{"id":"6282176680026@s.whatsapp.net","limit":3},{"id":"6285326354975@s.whatsapp.net","limit":4},{"id":"6281368593367@s.whatsapp.net","limit":4},{"id":"6285731558195@s.whatsapp.net","limit":2},{"id":"6287703403379@s.whatsapp.net","limit":3},{"id":"6285933819286@s.whatsapp.net","limit":2},{"id":"6281354133681@s.whatsapp.net","limit":1},{"id":"6285870054532@s.whatsapp.net","limit":-31},{"id":"6281217479556@s.whatsapp.net","limit":4},{"id":"628886234378@s.whatsapp.net","limit":-20105},{"id":"6289516337454@s.whatsapp.net","limit":2},{"id":"6285783454034@s.whatsapp.net","limit":8},{"id":"6287861004399@s.whatsapp.net","limit":4},{"id":"6283185274185@s.whatsapp.net","limit":8},{"id":"6285733329868@s.whatsapp.net","limit":2},{"id":"6285892257662@s.whatsapp.net","limit":11},{"id":"6283120880134@s.whatsapp.net","limit":1},{"id":"6285709467209@s.whatsapp.net","limit":2},{"id":"6283116710872@s.whatsapp.net","limit":5},{"id":"6283895984328@s.whatsapp.net","limit":20},{"id":"6289634037416@s.whatsapp.net","limit":3},{"id":"62895338895509@s.whatsapp.net","limit":6},{"id":"6287714741395@s.whatsapp.net","limit":2},{"id":"6281271597152@s.whatsapp.net","limit":3},{"id":"6285655807787@s.whatsapp.net","limit":1},{"id":"6285270594516@s.whatsapp.net","limit":3},{"id":"6282372858630@s.whatsapp.net","limit":14},{"id":"62895360238106@s.whatsapp.net","limit":-68229},{"id":"6282393142483@s.whatsapp.net","limit":1},{"id":"6285233389510@s.whatsapp.net","limit":3},{"id":"6285785964164@s.whatsapp.net","limit":2},{"id":"6283194692802@s.whatsapp.net","limit":20},{"id":"6282358389609@s.whatsapp.net","limit":20},{"id":"62895322217284@s.whatsapp.net","limit":3},{"id":"6285876176122@s.whatsapp.net","limit":1},{"id":"6285333328220@s.whatsapp.net","limit":9},{"id":"6282163979823@s.whatsapp.net","limit":3},{"id":"6285726092097@s.whatsapp.net","limit":2},{"id":"628971108582@s.whatsapp.net","limit":4},{"id":"6289676079613@s.whatsapp.net","limit":2},{"id":"6285814269121@s.whatsapp.net","limit":1},{"id":"6289697366058@s.whatsapp.net","limit":7},{"id":"6283139068376@s.whatsapp.net","limit":13},{"id":"6281391760197@s.whatsapp.net","limit":6},{"id":"6289636141862@s.whatsapp.net","limit":2},{"id":"6282279516874@s.whatsapp.net","limit":19},{"id":"628989227518@s.whatsapp.net","limit":4},{"id":"6287883394506@s.whatsapp.net","limit":5},{"id":"6283172939140@s.whatsapp.net","limit":5},{"id":"6285700690897@s.whatsapp.net","limit":16},{"id":"6283135934377@s.whatsapp.net","limit":3},{"id":"6281261664016@s.whatsapp.net","limit":1},{"id":"6285817680437@s.whatsapp.net","limit":6},{"id":"6282182301992@s.whatsapp.net","limit":3},{"id":"6282274016644@s.whatsapp.net","limit":7},{"id":"6282265451262@s.whatsapp.net","limit":6},{"id":"6285768105325@s.whatsapp.net","limit":16},{"id":"6283134191967@s.whatsapp.net","limit":4},{"id":"6285772697364@s.whatsapp.net","limit":2},{"id":"6281361612013@s.whatsapp.net","limit":2},{"id":"6283148966403@s.whatsapp.net","limit":1},{"id":"6285758005752@s.whatsapp.net","limit":2},{"id":"6285702283717@s.whatsapp.net","limit":20},{"id":"60128732721@s.whatsapp.net","limit":5},{"id":"6285871049149@s.whatsapp.net","limit":9},{"id":"628989832856@s.whatsapp.net","limit":2},{"id":"6285708742482@s.whatsapp.net","limit":1},{"id":"6285735705471@s.whatsapp.net","limit":1},{"id":"6287875369113@s.whatsapp.net","limit":3},{"id":"6283192274007@s.whatsapp.net","limit":2},{"id":"6283199733727@s.whatsapp.net","limit":2},{"id":"62895610116371@s.whatsapp.net","limit":5},{"id":"6281362768137@s.whatsapp.net","limit":15},{"id":"6281315824062@s.whatsapp.net","limit":2},{"id":"6285238308932@s.whatsapp.net","limit":3},{"id":"6288262808696@s.whatsapp.net","limit":21},{"id":"6285697621225@s.whatsapp.net","limit":11},{"id":"6283895252188@s.whatsapp.net","limit":4},{"id":"628979883499@s.whatsapp.net","limit":2},{"id":"60182093715@s.whatsapp.net","limit":4},{"id":"6285270655197@s.whatsapp.net","limit":2},{"id":"6285705473185@s.whatsapp.net","limit":9},{"id":"62895613477235@s.whatsapp.net","limit":9},{"id":"6281211002360@s.whatsapp.net","limit":2},{"id":"6285815469368@s.whatsapp.net","limit":7},{"id":"6282216249310@s.whatsapp.net","limit":10},{"id":"60108142264@s.whatsapp.net","limit":3},{"id":"6285331225693@s.whatsapp.net","limit":2},{"id":"6281253714973@s.whatsapp.net","limit":6},{"id":"6282157943253@s.whatsapp.net","limit":4},{"id":"6281334703842@s.whatsapp.net","limit":1},{"id":"62887436155766@s.whatsapp.net","limit":7},{"id":"","limit":0},{"id":"6281376078098@s.whatsapp.net","limit":20},{"id":"6282216257487@s.whatsapp.net","limit":2},{"id":"6285750049697@s.whatsapp.net","limit":15},{"id":"6281803623430@s.whatsapp.net","limit":4},{"id":"6285876330812@s.whatsapp.net","limit":1},{"id":"6287789298285@s.whatsapp.net","limit":2},{"id":"6281217721509@s.whatsapp.net","limit":2},{"id":"6285714893557@s.whatsapp.net","limit":5},{"id":"6283827825087@s.whatsapp.net","limit":1},{"id":"6283831795437@s.whatsapp.net","limit":4},{"id":"6287720541943@s.whatsapp.net","limit":2},{"id":"628997989162@s.whatsapp.net","limit":3},{"id":"6281268657531@s.whatsapp.net","limit":5},{"id":"6285752754192@s.whatsapp.net","limit":4},{"id":"6282339600466@s.whatsapp.net","limit":2},{"id":"6289647592181@s.whatsapp.net","limit":5},{"id":"6285334599761@s.whatsapp.net","limit":1},{"id":"6285656615441@s.whatsapp.net","limit":-52},{"id":"6282292035694@s.whatsapp.net","limit":3},{"id":"6282124828903@s.whatsapp.net","limit":3},{"id":"6281253707930@s.whatsapp.net","limit":3},{"id":"6285783697784@s.whatsapp.net","limit":6},{"id":"6289671536140@s.whatsapp.net","limit":4},{"id":"6283103558038@s.whatsapp.net","limit":2},{"id":"6285602885413@s.whatsapp.net","limit":1},{"id":"6281278427603@s.whatsapp.net","limit":3},{"id":"6283805211681@s.whatsapp.net","limit":8},{"id":"6282283068962@s.whatsapp.net","limit":9},{"id":"6281259306401@s.whatsapp.net","limit":3},{"id":"6285643938712@s.whatsapp.net","limit":12},{"id":"6282123597536@s.whatsapp.net","limit":7},{"id":"6282159571051@s.whatsapp.net","limit":4},{"id":"6282338098038@s.whatsapp.net","limit":-3},{"id":"6282322307564@s.whatsapp.net","limit":4},{"id":"628179814788@s.whatsapp.net","limit":18},{"id":"6283802672648@s.whatsapp.net","limit":-1},{"id":"62895703704777@s.whatsapp.net","limit":4},{"id":"6285864306455@s.whatsapp.net","limit":5},{"id":"6283146858557@s.whatsapp.net","limit":3},{"id":"6287884640190@s.whatsapp.net","limit":2},{"id":"628113907926@s.whatsapp.net","limit":8},{"id":"6285785457212@s.whatsapp.net","limit":2},{"id":"62895617127010@s.whatsapp.net","limit":0},{"id":"628813585336@s.whatsapp.net","limit":5},{"id":"6285245926180@s.whatsapp.net","limit":2},{"id":"6283865169796@s.whatsapp.net","limit":-1096},{"id":"6289503077219@s.whatsapp.net","limit":2},{"id":"6281240946525@s.whatsapp.net","limit":0},{"id":"6283848933674@s.whatsapp.net","limit":-13},{"id":"6283180040410@s.whatsapp.net","limit":1},{"id":"6282327312170@s.whatsapp.net","limit":2},{"id":"6282144469727@s.whatsapp.net","limit":-2017},{"id":"628815788705@s.whatsapp.net","limit":2},{"id":"6285227433977@s.whatsapp.net","limit":-4},{"id":"6281996261392@s.whatsapp.net","limit":2},{"id":"62895619634189@s.whatsapp.net","limit":11},{"id":"6287847982434@s.whatsapp.net","limit":1},{"id":"6285959595524@s.whatsapp.net","limit":0},{"id":"6285695331107@s.whatsapp.net","limit":4},{"id":"6285341224082@s.whatsapp.net","limit":1},{"id":"6288803562994@s.whatsapp.net","limit":10},{"id":"6282261055605@s.whatsapp.net","limit":-1},{"id":"6283154665504@s.whatsapp.net","limit":2},{"id":"6282177636962@s.whatsapp.net","limit":5},{"id":"6281543345083@s.whatsapp.net","limit":-8},{"id":"6282349677115@s.whatsapp.net","limit":-1},{"id":"6285947447507@s.whatsapp.net","limit":1},{"id":"6283155796381@s.whatsapp.net","limit":-3},{"id":"6281361187421@s.whatsapp.net","limit":2},{"id":"6282310561073@s.whatsapp.net","limit":-14},{"id":"6285764112841@s.whatsapp.net","limit":1},{"id":"6283807860448@s.whatsapp.net","limit":2},{"id":"6285813437079@s.whatsapp.net","limit":2},{"id":"6289531837247@s.whatsapp.net","limit":3},{"id":"6282282993291@s.whatsapp.net","limit":3},{"id":"628988285982@s.whatsapp.net","limit":1},{"id":"6283140308163@s.whatsapp.net","limit":-16},{"id":"6281316793135@s.whatsapp.net","limit":1}]